chunking/__init__.py
chunking/doc.py
chunking/docx.py
chunking/html.py
chunking/json.py
chunking/md.py
chunking/pdf.py
chunking/text.py
connector/__init__.py
connector/_common.py
connector/direct.py
agentset_chunker-1.0.1.dist-info/LICENSE.txt
agentset_chunker-1.0.1.dist-info/METADATA
agentset_chunker-1.0.1.dist-info/WHEEL
agentset_chunker-1.0.1.dist-info/top_level.txt
agentset_chunker-1.0.1.dist-info/RECORD
