Metadata-Version: 2.2
Name: agentset_chunker
Version: 1.0.1
Summary: agentset chunker
Home-page: https://github.com/agentset-ai/agentset-chunker
Author: MMMohebi
Author-email: MMMohebi@outlook.com
Requires-Python: >=3.12
License-File: LICENSE.txt
Requires-Dist: langchain-core>=0.3.41
Requires-Dist: loguru>=0.7.3
Requires-Dist: requests>=2.32.3
Requires-Dist: tqdm>=4.67.1
Requires-Dist: unstructured[csv,doc,docx,md,pdf]>=0.16.23
